MNCSimulator/__init__.py
MNCSimulator/server.py
MNCSimulator/tablet.py
mncsimulator-0.0.1.dist-info/licenses/LICENSE
mncsimulator-0.0.1.dist-info/METADATA
mncsimulator-0.0.1.dist-info/WHEEL
mncsimulator-0.0.1.dist-info/top_level.txt
mncsimulator-0.0.1.dist-info/RECORD
