Metadata-Version: 2.4
Name: MNCSimulator
Version: 0.0.1
Summary: A MNC Simulator
Author-email: Ishika Shali <Ishika.Shali@natus.com>
License-Expression: MIT
Classifier: Programming Language :: Python :: 3
Classifier: Operating System :: OS Independent
Requires-Python: >=3.9
License-File: LICENSE
Dynamic: license-file
